{
    "exerciseTitle": "Установка кодировки в UTF-8",
    "exerciseOrder": 3,
    "maxStep": 5,
    "preExercises": [
    ],

    "exerciseTargets": [
        {
            "order": 1,
            "text": "Научиться устанавливать кодировку UTF-8 для редактора Eclipse"
        }
    ],

    "exerciseSteps": [
        {
            "order": 1,
            "title": "Откройте окно настроек Eclipse"
        },
        {
            "order": 2,
            "title": "Откройте меню Workspace в настройках"
        },
        {
            "order": 3,
            "title": "В настройках Workspace найдите секцию <code>Text file encoding</code>"
        },
        {
            "order": 4,
            "title": "Смените кодировку на UTF-8"
        },
        {
            "order": 5,
            "title": "Сохраните изменения"
        }
    ]
}
